typeshell/.DS_Store
typeshell/__init__.py
typeshell/__main__.py
typeshell/testmanager/.DS_Store
typeshell/testmanager/TestManager.py
typeshell/testmanager/__init__.py
typeshell/testmanager/prompts.py
typeshell-0.1.2.dist-info/LICENSE
typeshell-0.1.2.dist-info/METADATA
typeshell-0.1.2.dist-info/WHEEL
typeshell-0.1.2.dist-info/entry_points.txt
typeshell-0.1.2.dist-info/top_level.txt
typeshell-0.1.2.dist-info/RECORD
